iris_validator/__init__.py
iris_validator/cmdline.py
iris_validator/iris_rules.py
iris_validator/iris_unit_names.py
iris_validator/iris_validate.py
iris_validator/iris_resources/402_pass.xml
iris_validator/iris_resources/408.xml
iris_validator/iris_resources/410-pass.xml
iris_validator/iris_resources/411_CI_ABL.xml
iris_validator/iris_resources/ANMO_BHZ.xml
iris_validator/iris_resources/ANMO_BHZ_epoch_overlap.xml
iris_validator/iris_resources/ANMO_BHZ_nosensor_description_310.xml
iris_validator/iris_resources/AUMCQBHZ_stageNOSEQUENCE.xml
iris_validator/iris_resources/CIABLEHZ_block61NoCoeff.xml
iris_validator/iris_resources/CI_ADL.xml
iris_validator/iris_resources/CODEIUANMOBHZ.xml
iris_validator/iris_resources/F1_101.xml
iris_validator/iris_resources/F1_110.xml
iris_validator/iris_resources/F1_111.xml
iris_validator/iris_resources/F1_112.xml
iris_validator/iris_resources/F1_201.xml
iris_validator/iris_resources/F1_210.xml
iris_validator/iris_resources/F1_211.xml
iris_validator/iris_resources/F1_212.xml
iris_validator/iris_resources/F1_220.xml
iris_validator/iris_resources/F1_222.xml
iris_validator/iris_resources/F1_223.xml
iris_validator/iris_resources/F1_301.xml
iris_validator/iris_resources/F1_302.xml
iris_validator/iris_resources/F1_303.xml
iris_validator/iris_resources/F1_304.xml
iris_validator/iris_resources/F1_305.xml
iris_validator/iris_resources/F1_310.xml
iris_validator/iris_resources/F1_320.xml
iris_validator/iris_resources/F1_321.xml
iris_validator/iris_resources/F1_322.xml
iris_validator/iris_resources/F1_330.xml
iris_validator/iris_resources/F1_331.xml
iris_validator/iris_resources/F1_332.xml
iris_validator/iris_resources/F1_333.xml
iris_validator/iris_resources/F1_334.xml
iris_validator/iris_resources/F1_401.xml
iris_validator/iris_resources/F1_402.xml
iris_validator/iris_resources/F1_403.xml
iris_validator/iris_resources/F1_404.xml
iris_validator/iris_resources/F1_405.xml
iris_validator/iris_resources/F1_406.xml
iris_validator-0.0.3.dist-info/AUTHORS.rst
iris_validator-0.0.3.dist-info/LICENSE
iris_validator-0.0.3.dist-info/METADATA
iris_validator-0.0.3.dist-info/WHEEL
iris_validator-0.0.3.dist-info/entry_points.txt
iris_validator-0.0.3.dist-info/top_level.txt
iris_validator-0.0.3.dist-info/RECORD
